Metadata-Version: 2.1
Name: stilts-wrapper
Version: 0.1.0.2
Summary: Thin wrapper around astro STILTS
Home-page: https://github.com/aidansedgewick/stilts_wrapper
Author: Aidan S
Author-email: aidansedgewick@gmail.com
License: MIT license
Platform: UNKNOWN
License-File: LICENSE
